LICENSE
MANIFEST.in
README.md
requirements.txt
requirements2.txt
setup.cfg
setup.py
bin/lbcurl
requests_lb/__init__.py
requests_lb/lbcurl.py
requests_lb/requests_lb.py
requests_lb.egg-info/PKG-INFO
requests_lb.egg-info/SOURCES.txt
requests_lb.egg-info/dependency_links.txt
requests_lb.egg-info/requires.txt
requests_lb.egg-info/top_level.txt