Metadata-Version: 1.0
Name: requests-lb
Version: 0.3.1
Summary: A load-balancing wrapper around requests
Home-page: UNKNOWN
Author: ['John-John Tedro']
Author-email: ['udoprog@tedro.se']
License: Apache 2.0
Platform: UNKNOWN
